Metadata-Version: 1.1
Name: SourceSpell
Version: 1.1
Summary: Command line spellchecker for source code files.
Home-page: https://s-knibbs.github.io/sourcespell
Author: Simon J Knibbs
Author-email: simon.knibbs@gmail.com
License: GPLv3
Download-URL: https://github.com/s-knibbs/sourcespell/tarball/1.1
Platform: any
Classifier: Programming Language :: Python
Classifier: Development Status :: 4 - Beta
Classifier: Environment :: Console
Classifier: Intended Audience :: Developers
Classifier: License :: OSI Approved :: GNU General Public License v3 (GPLv3)
Classifier: Operating System :: OS Independent
Classifier: Topic :: Software Development :: Quality Assurance
